wfx_common_tools/__init__.py
wfx_common_tools/connection/SshTarget.py
wfx_common_tools/connection/__init__.py
wfx_common_tools/connection/wfx_connection.py
wfx_common_tools/pta/__init__.py
wfx_common_tools/pta/wfx_pta.py
wfx_common_tools/pta/wfx_pta_data.py
wfx_common_tools/test_feature/__init__.py
wfx_common_tools/test_feature/definitions.in
wfx_common_tools/test_feature/job.py
wfx_common_tools/test_feature/pds_compress.py
wfx_common_tools/test_feature/wfx_pds_tree.py
wfx_common_tools/test_feature/wfx_test_dut.py
wfx_common_tools/test_feature/wfx_test_target.py
wfx_common_tools-5.5.3.dist-info/METADATA
wfx_common_tools-5.5.3.dist-info/WHEEL
wfx_common_tools-5.5.3.dist-info/licenses/LICENSE
wfx_common_tools-5.5.3.dist-info/RECORD
