Metadata-Version: 2.4
Name: wfx_common_tools
Version: 5.5.3
Summary: Silicon Laboratories WFx Wi-Fi tools for all supported platforms
Project-URL: Homepage, https://github.com/SiliconLabs/wfx-common-tools
Project-URL: Issues, https://github.com/SiliconLabs/wfx-common-tools/issues
Author-email: silabs-Marc <marc.dorval@silabs.com>
Maintainer-email: silabs-tuD <tu.dao@silabs.com>, silabs-JulienT <julien.tiron@silabs.com>, silabs-Marc <marc.dorval@silabs.com>
License-File: LICENSE
Classifier: License :: OSI Approved :: Apache Software License
Classifier: Operating System :: OS Independent
Classifier: Programming Language :: Python :: 3
Requires-Python: >=3.9
Requires-Dist: ifaddr>=0.1.6
Requires-Dist: paramiko>=2.7.1
Requires-Dist: pyserial>=3.4
